streamlit_auth/__init__.py
streamlit_auth/check_token.py
gsc_example_streamlit_access_check-0.0.1.dist-info/LICENSE.txt
gsc_example_streamlit_access_check-0.0.1.dist-info/METADATA
gsc_example_streamlit_access_check-0.0.1.dist-info/WHEEL
gsc_example_streamlit_access_check-0.0.1.dist-info/top_level.txt
gsc_example_streamlit_access_check-0.0.1.dist-info/RECORD
