Metadata-Version: 2.1
Name: gsc-example-streamlit-access-check
Version: 0.0.1
Summary: sample gsc lib
Author: byungjebang
Author-email: byungjebang@mz.co.kr
Classifier: Programming Language :: Python :: 3
Classifier: License :: OSI Approved :: MIT License
Classifier: Operating System :: OS Independent
Requires-Python: >=3.5
License-File: LICENSE.txt
